{"users":[{"id":5,"name":"Murilo Amancio 1","email":"muriloamancio0@gmail.com","password":"123123","profile":"ADM","work_days":["Seg","Qua"],"work_hours":[6,7,8]},{"id":6,"name":"Helena","email":"helena@teste.com","password":"123123","profile":"ADM"},{"id":7,"name":"Murilo muito lindo ","email":"murilo@teste.com","password":"123123","profile":"ADM"},{"id":8,"name":"asdasdasdas","email":"m@m.com","password":"123123","profile":"ADM"},{"id":9,"name":"asdasdasdas","email":"mm@m.com","password":"123123","profile":"ADM"},{"id":10,"name":"asdasdasdas","email":"mm@m.com","password":"123123","profile":"ADM"},{"id":11,"name":"dsdsds","email":"sdsd@teste.com","password":"123123","profile":"ADM"},{"id":12,"name":"mu","email":"we@teste.com","password":"123123","profile":"ADM"},{"id":13,"name":"juju","email":"juju@g.com","password":"123123","profile":"ADM"},{"id":14,"name":"teste","email":"teste4@teste.com","password":"123123","profile":"ADM"},{"id":15,"name":"jonas","email":"jonas@teste.com","password":"123123","profile":"ADM"},{"id":16,"name":"teste","email":"teste6@teste.com","password":"123123","profile":"ADM"},{"id":17,"name":"koe","email":"koe@koe.com","password":"123123","profile":"ADM"}],"adm_users":[],"barbershop":[{"id":2,"user_id":"5","name":"Barbearia X","email":"barbeariax@gmail.com","opening_days":["Seg","Qua","Sab"],"opening_hours":[6,7,8,9,18,19,20,12,13]},{"id":3,"user_id":"15","name":"xicavirus ","email":"xicavirus@teste.com","opening_days":["Qua","Sex","Sab","Dom"],"opening_hours":[7,8,9,10,11,14,15,16,17]},{"id":4,"user_id":"16","name":"feira junina","email":"julhos@teste.com","opening_days":["Ter"],"opening_hours":[10,11,9,8]},{"id":5,"user_id":"17","name":"discoteca","email":"discoteca@somdisc.com","opening_days":["Seg","Ter","Qua","Dom"],"opening_hours":[4,10,16,22,19,13,7,1,6,11,20,21]}],"schedules":[{"id":1,"barbershop_id":2,"user_id":5,"client_name":"teste","date":"2023-08-09T00:00:00.000Z","time":8}]}